RNAformer/__init__.py
RNAformer/model/RNAformer.py
RNAformer/model/RNAformer_block.py
RNAformer/model/RNAformer_stack.py
RNAformer/model/__init__.py
RNAformer/module/__init__.py
RNAformer/module/axial_attention.py
RNAformer/module/axial_dropout.py
RNAformer/module/embedding.py
RNAformer/module/feed_forward.py
RNAformer/pl_module/__init__.py
RNAformer/pl_module/datamodule_rna.py
RNAformer/pl_module/rna_folding_trainer.py
RNAformer/utils/__init__.py
RNAformer/utils/configuration.py
RNAformer/utils/eval_predictions.py
RNAformer/utils/folder_manager.py
RNAformer/utils/group_parameters.py
RNAformer/utils/instantiate.py
RNAformer/utils/logger.py
RNAformer/utils/data/__init__.py
RNAformer/utils/data/rna.py
RNAformer/utils/handler/__init__.py
RNAformer/utils/handler/base_handler.py
RNAformer/utils/handler/checkpoint.py
RNAformer/utils/handler/folder.py
RNAformer/utils/optim/__init__.py
RNAformer/utils/optim/lr_schedule.py
RNAformer-1.3.2.dist-info/LICENSE
RNAformer-1.3.2.dist-info/METADATA
RNAformer-1.3.2.dist-info/WHEEL
RNAformer-1.3.2.dist-info/top_level.txt
RNAformer-1.3.2.dist-info/RECORD
