Metadata-Version: 2.1
Name: RNAformer
Version: 1.3.2
Summary: RNAformer: a simple single-sequence-based deep learning model for RNA secondary structure prediction.
Author: Frederic Runge, Rolf Backofen, Frank Hutter
Author-email: "Joerg K.H. Franke" <frankej@cs.uni-freiburg.de>, Ryan Koeksal <koeksalr@informatik.uni-freiburg.de>
Maintainer-email: Ryan Koeksal <koeksalr@informatik.uni-freiburg.de>, "Joerg K.H. Franke" <frankej@cs.uni-freiburg.de>
Project-URL: Homepage, https://github.com/automl/RNAformer
Project-URL: Issues, https://github.com/automl/RNAformer/issues
Classifier: Programming Language :: Python :: 3
Requires-Python: >=3.10
License-File: LICENSE
Requires-Dist: torch
Requires-Dist: torchvision
Requires-Dist: torchaudio
Requires-Dist: tqdm
Requires-Dist: pyyaml
Requires-Dist: pyaml
Requires-Dist: numpy
Requires-Dist: packaging
Requires-Dist: wheel
Requires-Dist: tabulate
Requires-Dist: scipy
Requires-Dist: pandas ==2.0.2
Requires-Dist: scikit-learn ==1.3.0
Requires-Dist: matplotlib ==3.7.2
Requires-Dist: polars
Requires-Dist: loralib ==0.1.2
Requires-Dist: tensorboard ==2.13.0
Requires-Dist: transformers
Requires-Dist: datasets ==2.13.1
Requires-Dist: pytorch-lightning ==2.0.4
Requires-Dist: deepspeed ==0.9.5
Requires-Dist: rotary-embedding-torch
